rusyll/.pytest_cache/.gitignore
rusyll/.pytest_cache/CACHEDIR.TAG
rusyll/.pytest_cache/README.md
rusyll/.pytest_cache/v/cache/nodeids
rusyll/.pytest_cache/v/cache/stepwise
rusyll/__init__.py
rusyll/rusyll.py
rusyll-0.1.1.dist-info/entry_points.txt
rusyll-0.1.1.dist-info/WHEEL
rusyll-0.1.1.dist-info/METADATA
rusyll-0.1.1.dist-info/RECORD
