Metadata-Version: 2.1
Name: rusyll
Version: 0.1.1
Summary: Splitting Russian words into phonetic syllables
Home-page: https://github.com/weiss-d/rusyll
License: MIT
Keywords: syllables,Russian,language,phonetic,phonology
Author: Simon Weiss
Author-email: wonder@simonweiss.space
Requires-Python: >=3.7,<4.0
Classifier: License :: OSI Approved :: MIT License
Classifier: Programming Language :: Python :: 3
Classifier: Programming Language :: Python :: 3.7
Classifier: Programming Language :: Python :: 3.8
Project-URL: Repository, https://github.com/weiss-d/rusyll
